COPYING
MANIFEST.in
README.rst
__init__.py
ctff.c
setup.py
tff.py
tff.egg-info/PKG-INFO
tff.egg-info/SOURCES.txt
tff.egg-info/dependency_links.txt
tff.egg-info/eager_resources.txt
tff.egg-info/not-zip-safe
tff.egg-info/top_level.txt