Metadata-Version: 1.0
Name: tff
Version: 0.2.10
Summary: Terminal Filter Framework
Home-page: https://github.com/saitoha/tff
Author: Hayaki Saito (user@zuse.jp)
Author-email: user@zuse.jp
License: MIT
Keywords: terminal filter
Platform: UNKNOWN
Classifier: Development Status :: 4 - Beta
Classifier: Topic :: Terminals
Classifier: Environment :: Console
Classifier: Intended Audience :: Developers
Classifier: License :: OSI Approved :: MIT License
Classifier: Programming Language :: Python
